LICENSE
word2quiz/__init__.py
word2quiz/locales/en/LC_MESSAGES/base.po
word2quiz/main.py
word2quiz-0.2.2.dist-info/LICENSE
word2quiz-0.2.2.dist-info/WHEEL
word2quiz-0.2.2.dist-info/METADATA
word2quiz-0.2.2.dist-info/RECORD
