Metadata-Version: 2.1
Name: word2quiz
Version: 0.2.2
Summary: Create quizzes in Canvas from simple Word docx files using CanvasRobot/Canvasapi
Home-page: https://github.com/ndegroot/word2quiz
Author: Nico de Groot
Author-email: ndegroot0@gmail.com
Requires-Python: >=3.10,<4.0
Classifier: Programming Language :: Python :: 3
Classifier: Programming Language :: Python :: 3.10
Classifier: Programming Language :: Python :: 3.11
Requires-Dist: Pillow (>=9.1.0,<10.0.0)
Requires-Dist: attrs (>=22.1.0,<23.0.0)
Requires-Dist: canvasapi (>=3.0.0,<4.0.0)
Requires-Dist: canvasrobot
Requires-Dist: docx2python (>=2.0.4,<3.0.0)
Requires-Dist: keyring (>=23.6.0,<24.0.0)
Requires-Dist: python-docx (>=0.8.11,<0.9.0)
Requires-Dist: requests (>=2.27.1,<3.0.0)
Requires-Dist: rich (>=12.4.4,<13.0.0)
Project-URL: Repository, https://github.com/ndegroot/word2quiz
